BianchengRumenZhinanXiaojingMo/README.md
BianchengRumenZhinanXiaojingMo/__init__.py
BianchengRumenZhinanXiaojingMo/__main__.py
BianchengRumenZhinanXiaojingMo/file.epub
BianchengRumenZhinanXiaojingMo/index.html
BianchengRumenZhinanXiaojingMo/css/__init__.py
BianchengRumenZhinanXiaojingMo/css/annotations.css
BianchengRumenZhinanXiaojingMo/css/main.css
BianchengRumenZhinanXiaojingMo/css/normalize.css
BianchengRumenZhinanXiaojingMo/css/popup.css
BianchengRumenZhinanXiaojingMo/font/__init__.py
BianchengRumenZhinanXiaojingMo/font/fontello.eot
BianchengRumenZhinanXiaojingMo/font/fontello.svg
BianchengRumenZhinanXiaojingMo/font/fontello.ttf
BianchengRumenZhinanXiaojingMo/font/fontello.woff
BianchengRumenZhinanXiaojingMo/img/__init__.py
BianchengRumenZhinanXiaojingMo/img/annotator-glyph-sprite.png
BianchengRumenZhinanXiaojingMo/img/annotator-icon-sprite.png
BianchengRumenZhinanXiaojingMo/img/apple-touch-icon.png
BianchengRumenZhinanXiaojingMo/img/cancelfullscreen.png
BianchengRumenZhinanXiaojingMo/img/close.png
BianchengRumenZhinanXiaojingMo/img/fullscreen.png
BianchengRumenZhinanXiaojingMo/img/loader.gif
BianchengRumenZhinanXiaojingMo/img/menu-icon.png
BianchengRumenZhinanXiaojingMo/img/save.png
BianchengRumenZhinanXiaojingMo/img/saved.png
BianchengRumenZhinanXiaojingMo/img/settings-s.png
BianchengRumenZhinanXiaojingMo/img/settings.png
BianchengRumenZhinanXiaojingMo/img/star.png
BianchengRumenZhinanXiaojingMo/js/__init__.py
BianchengRumenZhinanXiaojingMo/js/epub.js
BianchengRumenZhinanXiaojingMo/js/epub.min.js
BianchengRumenZhinanXiaojingMo/js/epub.min.map
BianchengRumenZhinanXiaojingMo/js/hooks.min.js
BianchengRumenZhinanXiaojingMo/js/hooks.min.map
BianchengRumenZhinanXiaojingMo/js/reader.js
BianchengRumenZhinanXiaojingMo/js/reader.js.map
BianchengRumenZhinanXiaojingMo/js/reader.min.js
BianchengRumenZhinanXiaojingMo/js/reader.min.map
BianchengRumenZhinanXiaojingMo/js/hooks/__init__.py
BianchengRumenZhinanXiaojingMo/js/hooks/extensions/__init__.py
biancheng_rumen_zhinan_xiaojing_mo-2024.3.1.0.dist-info/METADATA
biancheng_rumen_zhinan_xiaojing_mo-2024.3.1.0.dist-info/WHEEL
biancheng_rumen_zhinan_xiaojing_mo-2024.3.1.0.dist-info/entry_points.txt
biancheng_rumen_zhinan_xiaojing_mo-2024.3.1.0.dist-info/top_level.txt
biancheng_rumen_zhinan_xiaojing_mo-2024.3.1.0.dist-info/RECORD
